basalam.hermes_messaging_sdk-0.0.5-py3.14-nspkg.pth
basalam/hermes_messaging_sdk/__init__.py
basalam/hermes_messaging_sdk/async_client.py
basalam/hermes_messaging_sdk/client.py
basalam/hermes_messaging_sdk/exceptions.py
basalam_hermes_messaging_sdk-0.0.5.dist-info/licenses/LICENSE
basalam_hermes_messaging_sdk-0.0.5.dist-info/METADATA
basalam_hermes_messaging_sdk-0.0.5.dist-info/WHEEL
basalam_hermes_messaging_sdk-0.0.5.dist-info/namespace_packages.txt
basalam_hermes_messaging_sdk-0.0.5.dist-info/top_level.txt
basalam_hermes_messaging_sdk-0.0.5.dist-info/RECORD
