Metadata-Version: 2.4
Name: basalam.hermes-messaging-sdk
Version: 0.0.5
Summary: Python SDK to integrate and interact with Hermes Marketing Automation Platform
Home-page: https://github.com/basalam/hermes-messaging-sdk
Author: Hasan Golparvar
Author-email: h.golparvar1383@gmail.com
Keywords: hermes marketing automation messaging sdk api client
Classifier: Development Status :: 4 - Beta
Classifier: Intended Audience :: Developers
Classifier: License :: OSI Approved :: MIT License
Classifier: Programming Language :: Python :: 3
Classifier: Programming Language :: Python :: 3.8
Classifier: Programming Language :: Python :: 3.9
Classifier: Programming Language :: Python :: 3.10
Classifier: Programming Language :: Python :: 3.11
Classifier: Programming Language :: Python :: 3.12
Classifier: Operating System :: OS Independent
Requires-Python: >=3.8
License-File: LICENSE
Requires-Dist: httpx>=0.24.0
Dynamic: author
Dynamic: author-email
Dynamic: classifier
Dynamic: description
Dynamic: description-content-type
Dynamic: home-page
Dynamic: keywords
Dynamic: license-file
Dynamic: requires-dist
Dynamic: requires-python
Dynamic: summary
